LICENSE
MANIFEST.in
README.md
VERSION
docker-network-capture
setup.py
dnc/__init__.py
dnc/pipeline/__init__.py
dnc/utils/__init__.py
docker_network_capture.egg-info/PKG-INFO
docker_network_capture.egg-info/SOURCES.txt
docker_network_capture.egg-info/dependency_links.txt
docker_network_capture.egg-info/requires.txt
docker_network_capture.egg-info/top_level.txt