Metadata-Version: 1.1
Name: docker-network-capture
Version: 0.6.1
Summary: Thin wrapper around Docker and tcpdump to get traffic coming from/to a container
Home-page: https://github.com/shaded-enmity/docker-network-capture
Author: Pavel Odvody
Author-email: podvody@redhat.com
License: GNU/GPLv2
Keywords: docker cli network traffic capture
Platform: UNKNOWN
Classifier: Programming Language :: Python :: 3 :: Only
